{"digest":"6199b2b5d3b6d5635fbef381b97f3168ea5f5372","css":".github-StagingView {\n  flex: 1;\n  display: flex;\n  flex-direction: column;\n}\n.github-StagingView-group {\n  flex: 1;\n  display: flex;\n  flex-direction: column;\n}\n.github-StagingView-header {\n  display: flex;\n  align-items: center;\n  padding: 0 0 0 14px;\n  font-weight: 600;\n  border-top: 1px solid #1e1e1e;\n  border-bottom: 1px solid #1e1e1e;\n}\n.github-UnstagedChanges > .github-StagingView-header {\n  border-top: none;\n}\n.github-StagingView-header .icon {\n  text-align: center;\n}\n.github-StagingView-header .icon:before {\n  color: #797979;\n  margin-right: 11.66666667px;\n  vertical-align: middle;\n}\n.github-StagingView-headerButton {\n  height: 2.5em;\n  border: none;\n  padding: 0 14px;\n  font-weight: normal;\n  border-left: 1px solid #1e1e1e;\n  white-space: nowrap;\n  background: none;\n  cursor: default;\n}\n.github-StagingView-headerButton:disabled {\n  color: #797979;\n}\n.github-StagingView-headerButton:active {\n  background-color: #454545;\n}\n.github-StagingView-headerButton.icon:before {\n  margin-right: 0;\n  font-size: 1em;\n  text-align: left;\n}\n.github-StagingView-headerButton--fullWidth {\n  border-left: none;\n  border-bottom: 1px solid #1e1e1e;\n}\n.github-StagingView-headerButton--iconOnly:before {\n  width: auto;\n}\n.github-StagingView-title {\n  flex: 1;\n  margin-right: 14px;\n  line-height: 2.5em;\n  overflow: hidden;\n  text-overflow: ellipsis;\n  white-space: nowrap;\n}\n.github-StagingView-list {\n  flex: 1 1 0;\n  overflow-x: auto;\n}\n.github-StagingView-group-truncatedMsg {\n  padding: 7px 14px;\n}\n.github-StagingView-group.is-focused .is-selected {\n  color: #FFFFFF;\n  background: #404040;\n}\n.github-StagingView:focus .github-StagingView-group.is-focused .is-selected {\n  color: #ffffff;\n  background: #6D9CBE;\n}\n","imports":[{"path":"static/variables/ui-variables.less","digest":"b28ed6c38c4cfce23f83a1b012a3968aa63fce4c"},{"path":"static/variables/syntax-variables.less","digest":"812c1b7883a023f768773d14294653adcdb932d7"},{"path":"node_modules/github/styles/variables.less","digest":"85a0207ec11fe3c036e298e955d8b5d8fdd94742"},{"path":"/home/aimorris/.atom/packages/afterglow-ui/styles/ui-variables.less","digest":"9cf46eb826fd3b37e2057159d301306cd62a624f"},{"path":"/home/aimorris/.atom/packages/afterglow-syntax/styles/syntax-variables.less","digest":"5907346c5e2b8debe2f31c2cc7349f864f473ad7"},{"path":"/home/aimorris/.atom/packages/afterglow-syntax/styles/colors.less","digest":"163f81196e9fe054585090540b006023eb8857b7"},{"path":"/home/aimorris/.atom/packages/afterglow-ui/styles/colors.less","digest":"c08ad57aaa6b4f9fe8749812fd453f3d9e0243cc"},{"path":"/home/aimorris/.atom/packages/afterglow-syntax/styles/syntax-variables.less","digest":"5907346c5e2b8debe2f31c2cc7349f864f473ad7"}],"version":1}